safedict/__init__.py
safedict/safedict.py
safe_dict-1.0.7.dist-info/METADATA
safe_dict-1.0.7.dist-info/WHEEL
safe_dict-1.0.7.dist-info/top_level.txt
safe_dict-1.0.7.dist-info/RECORD
