Metadata-Version: 2.2
Name: safe-dict
Version: 1.0.7
Home-page: https://github.com/robbinhust/safe-dict
Author: robinhust
Classifier: Programming Language :: Python :: 3
Classifier: License :: OSI Approved :: MIT License
Classifier: Operating System :: OS Independent
